asynclog/__init__.py
asynclog/handler.py
asynclog/tests/__init__.py
asynclog/tests/test_handler.py
asynclog-0.1.6.dist-info/METADATA
asynclog-0.1.6.dist-info/RECORD
asynclog-0.1.6.dist-info/WHEEL
asynclog-0.1.6.dist-info/top_level.txt
