Metadata-Version: 2.1
Name: asynclog
Version: 0.1.6
Summary: Asynchronous log for python logging.
Home-page: https://github.com/unpluggedcoder/asynclog
Author: unpluggedcoder
Author-email: unpluggedcoder@outlook.com
License: MIT
Keywords: logging asynchronous
Platform: UNKNOWN
Classifier: Programming Language :: Python :: 3
Classifier: Programming Language :: Python :: 3.5
Classifier: Programming Language :: Python :: 3.6
Classifier: Programming Language :: Python :: Implementation :: CPython
Classifier: Programming Language :: Python :: Implementation :: PyPy
Classifier: Topic :: Software Development :: Libraries :: Python Modules
Classifier: Topic :: System :: Logging
